witrium/__init__.py
witrium/client.py
witrium/py.typed
witrium/types.py
witrium-0.6.0.dist-info/licenses/LICENSE
witrium-0.6.0.dist-info/METADATA
witrium-0.6.0.dist-info/WHEEL
witrium-0.6.0.dist-info/top_level.txt
witrium-0.6.0.dist-info/RECORD
